sqlmath-2023.9.25.dist-info/LICENSE
sqlmath-2023.9.25.dist-info/top_level.txt
sqlmath-2023.9.25.dist-info/WHEEL
sqlmath-2023.9.25.dist-info/METADATA
sqlmath-2023.9.25.dist-info/RECORD
sqlmath/__init__.py
sqlmath/sqlmath_dbapi2.py
sqlmath/_sqlmath.cpython-311-x86_64-linux-gnu.so
