Metadata-Version: 2.1
Name: sqlmath
Version: 2023.9.25
Summary: sqlite for datascience
Author: Kai Zhu
License: MIT
Project-URL: Homepage, https://github.com/sqlmath/sqlmath
Project-URL: Changelog, https://github.com/sqlmath/sqlmath/blob/master/CHANGELOG.md
Classifier: Development Status :: 4 - Beta
Classifier: Intended Audience :: Developers
Classifier: Intended Audience :: Science/Research
Classifier: License :: OSI Approved :: MIT License
Classifier: Operating System :: MacOS
Classifier: Operating System :: Microsoft :: Windows
Classifier: Operating System :: POSIX :: Linux
Classifier: Programming Language :: C
Classifier: Programming Language :: JavaScript
Classifier: Programming Language :: Python
Classifier: Topic :: Database
Classifier: Topic :: Scientific/Engineering
Classifier: Topic :: Software Development
Requires-Python: >=3.10
License-File: LICENSE
